arxiv_post/__init__.py
arxiv_post/apps/__init__.py
arxiv_post/apps/slack.py
arxiv_post/article.py
arxiv_post/arxiv.py
arxiv_post/cli.py
arxiv_post/consts.py
arxiv_post/deepl.py
arxiv_post-0.7.0.dist-info/LICENSE
arxiv_post-0.7.0.dist-info/METADATA
arxiv_post-0.7.0.dist-info/WHEEL
arxiv_post-0.7.0.dist-info/entry_points.txt
arxiv_post-0.7.0.dist-info/RECORD
