Metadata-Version: 2.1
Name: arxiv-post
Version: 0.7.0
Summary: Translate and post arXiv articles to Slack and various apps
Home-page: https://github.com/astropenguin/arxiv-post/
License: MIT
Keywords: arxiv,deepl,slack,translation
Author: Akio Taniguchi
Author-email: taniguchi@a.phys.nagoya-u.ac.jp
Requires-Python: >=3.8,<3.12
Classifier: License :: OSI Approved :: MIT License
Classifier: Programming Language :: Python :: 3
Classifier: Programming Language :: Python :: 3.8
Classifier: Programming Language :: Python :: 3.9
Classifier: Programming Language :: Python :: 3.10
Classifier: Programming Language :: Python :: 3.11
Requires-Dist: arxiv (>=1.4,<2.0)
Requires-Dist: dateparser (>=1.1,<2.0)
Requires-Dist: deepl (>=1.12,<2.0)
Requires-Dist: fire (>=0.5,<0.6)
Requires-Dist: more-itertools (>=9.0,<10.0)
Requires-Dist: playwright (>=1.30,<2.0)
Requires-Dist: pylatexenc (>=2.10,<3.0)
Requires-Dist: requests (>=2.28,<3.0)
Requires-Dist: tomli (>=2.0,<3.0)
Project-URL: Documentation, https://astropenguin.github.io/arxiv-post/
